mcdc/__init__.py
mcdc/adapt.py
mcdc/card.py
mcdc/config.py
mcdc/constant.py
mcdc/global_.py
mcdc/input_.py
mcdc/kernel.py
mcdc/loop.py
mcdc/main.py
mcdc/print_.py
mcdc/tally.py
mcdc/type_.py
mcdc/iqmc/__init__.py
mcdc/iqmc/iqmc_kernel.py
mcdc/iqmc/iqmc_loop.py
mcdc/src/algorithm.py
mcdc/src/geometry.py
mcdc/src/physics.py
mcdc/src/mesh/__init__.py
mcdc/src/mesh/structured.py
mcdc/src/mesh/uniform.py
mcdc/src/surface/__init__.py
mcdc/src/surface/common.py
mcdc/src/surface/cylinder_x.py
mcdc/src/surface/cylinder_y.py
mcdc/src/surface/cylinder_z.py
mcdc/src/surface/plane.py
mcdc/src/surface/plane_x.py
mcdc/src/surface/plane_y.py
mcdc/src/surface/plane_z.py
mcdc/src/surface/quadric.py
mcdc/src/surface/sphere.py
mcdc-0.12.0.dist-info/METADATA
mcdc-0.12.0.dist-info/WHEEL
mcdc-0.12.0.dist-info/licenses/LICENSE
mcdc-0.12.0.dist-info/RECORD
