Metadata-Version: 2.4
Name: mcdc
Version: 0.12.0
Summary: MC/DC (Monte Carlo Dynamic Code): a performant, scalable, and machine-portable Python-based Monte Carlo neutron transport package
Project-URL: Repository, https://github.com/CEMeNT-PSAAP/MCDC
Project-URL: Homepage, https://cement-psaap.github.io/
Project-URL: Documentation, https://mcdc.readthedocs.io/en/latest/
Project-URL: Issues, https://github.com/CEMeNT-PSAAP/MCDC/issues
Author: Caleb Shaw, Rohan Pankaj, Alexander Mote, Ethan Lame, Benjamin Whewell, Ryan G. McClarren, Todd S. Palmer, Lizhong Chen, Dmitriy Y. Anistratov, C. T. Kelley, Camille J. Palmer, Kyle E. Niemeyer
Author-email: Ilham Variansyah <variansi@oregonstate.edu>, Sam Pasmann <spasmann@nd.edu>, Joanna Morgan <morgajoa@oregonstate.edu>, Kayla Clements <clemekay@oregonstate.edu>, Braxton Cuneo <bcuneo@seattleu.edu>
Maintainer-email: Ilham Variansyah <variansi@oregonstate.edu>, Braxton Cuneo <bcuneo@seattleu.edu>, Kayla Clements <clemekay@oregonstate.edu>, Joanna Piper Morgan <morgajoa@oregonstate.edu>, "Kyle E. Niemeyer" <kyle.niemeyer@oregonstate.edu>
License: BSD 3-Clause License
License-File: LICENSE
Keywords: GPU,HPC,Monte Carlo,mpi4py,neutron transport,nuclear engineering,numba
Classifier: Intended Audience :: Science/Research
Classifier: License :: OSI Approved :: BSD License
Classifier: Natural Language :: English
Classifier: Operating System :: MacOS
Classifier: Operating System :: Unix
Classifier: Programming Language :: Python :: 3
Classifier: Typing :: Typed
Requires-Python: <3.12,>=3.9.1
Requires-Dist: black
Requires-Dist: colorama
Requires-Dist: cvxpy
Requires-Dist: h5py
Requires-Dist: matplotlib
Requires-Dist: mpi4py>=3.1.4
Requires-Dist: numba>=0.60.0
Requires-Dist: numpy
Requires-Dist: pre-commit
Requires-Dist: pytest
Requires-Dist: scipy
Requires-Dist: sympy
Provides-Extra: docs
Requires-Dist: furo; extra == 'docs'
Requires-Dist: sphinx-toolbox; extra == 'docs'
Requires-Dist: sphinx==7.2.6; extra == 'docs'
